setup.cfg
setup.py
pywincert.egg-info/PKG-INFO
pywincert.egg-info/SOURCES.txt
pywincert.egg-info/dependency_links.txt
pywincert.egg-info/not-zip-safe
pywincert.egg-info/top_level.txt
src/__init__.py
src/pywincert.py