Metadata-Version: 1.1
Name: pywincert
Version: 1.0.2
Summary: Wrapper for Windows makecert
Home-page: UNKNOWN
Author: Jim Carroll
Author-email: jim@carroll.net
License: UNKNOWN
Platform: UNKNOWN
Classifier: Development Status :: 5 - Production/Stable
Classifier: Environment :: Console
Classifier: Natural Language :: English
Classifier: Operating System :: OS Independent
